canva_connect_api-1.0.0.dist-info/licenses/LICENSE
openapi_client/__init__.py
openapi_client/api_client.py
openapi_client/api_response.py
openapi_client/configuration.py
openapi_client/exceptions.py
openapi_client/py.typed
openapi_client/rest.py
openapi_client/api/__init__.py
openapi_client/api/app_api.py
openapi_client/api/asset_api.py
openapi_client/api/autofill_api.py
openapi_client/api/brand_template_api.py
openapi_client/api/comment_api.py
openapi_client/api/connect_api.py
openapi_client/api/design_api.py
openapi_client/api/design_import_api.py
openapi_client/api/export_api.py
openapi_client/api/folder_api.py
openapi_client/api/oauth_api.py
openapi_client/api/resize_api.py
openapi_client/api/user_api.py
openapi_client/models/__init__.py
openapi_client/models/accepted_suggestion_event_type.py
openapi_client/models/add_suggested_edit.py
openapi_client/models/approval_request_action.py
openapi_client/models/approval_response_action.py
openapi_client/models/asset.py
openapi_client/models/asset_summary.py
openapi_client/models/asset_type.py
openapi_client/models/asset_upload_error.py
openapi_client/models/asset_upload_error_code.py
openapi_client/models/asset_upload_job.py
openapi_client/models/asset_upload_metadata.py
openapi_client/models/asset_upload_status.py
openapi_client/models/assigned_comment_event.py
openapi_client/models/autofill_error.py
openapi_client/models/autofill_error_code.py
openapi_client/models/boolean_data_table_cell.py
openapi_client/models/brand_template.py
openapi_client/models/capability.py
openapi_client/models/chart_data_field.py
openapi_client/models/comment.py
openapi_client/models/comment_content.py
openapi_client/models/comment_event.py
openapi_client/models/comment_event_deprecated.py
openapi_client/models/comment_event_type_enum.py
openapi_client/models/comment_notification_content.py
openapi_client/models/comment_thread_type.py
openapi_client/models/create_asset_upload_job_response.py
openapi_client/models/create_comment_request.py
openapi_client/models/create_comment_response.py
canva_connect_api-1.0.0.dist-info/METADATA
canva_connect_api-1.0.0.dist-info/WHEEL
canva_connect_api-1.0.0.dist-info/top_level.txt
canva_connect_api-1.0.0.dist-info/RECORD
