Metadata-Version: 2.4
Name: canva-connect-api
Version: 1.0.0
Summary: Unofficial Python client for Canva Connect API
Home-page: https://github.com/yourusername/canva-connect-api-python
Author: Canva Connect API Contributors
Author-email: Canva Connect API Contributors <contributors@example.com>
License: MIT
Project-URL: Homepage, https://github.com/yourusername/canva-connect-api-python
Project-URL: Documentation, https://github.com/yourusername/canva-connect-api-python#readme
Project-URL: Repository, https://github.com/yourusername/canva-connect-api-python
Project-URL: Bug Tracker, https://github.com/yourusername/canva-connect-api-python/issues
Project-URL: Changelog, https://github.com/yourusername/canva-connect-api-python/blob/main/CHANGELOG.md
Project-URL: Canva Connect API Docs, https://www.canva.dev/docs/connect/
Keywords: canva,connect,api,design,automation,graphics,templates
Classifier: Development Status :: 5 - Production/Stable
Classifier: Intended Audience :: Developers
Classifier: License :: OSI Approved :: MIT License
Classifier: Operating System :: OS Independent
Classifier: Programming Language :: Python :: 3
Classifier: Programming Language :: Python :: 3.9
Classifier: Programming Language :: Python :: 3.10
Classifier: Programming Language :: Python :: 3.11
Classifier: Programming Language :: Python :: 3.12
Classifier: Topic :: Internet :: WWW/HTTP :: Dynamic Content
Classifier: Topic :: Multimedia :: Graphics
Classifier: Topic :: Software Development :: Libraries :: Python Modules
Classifier: Topic :: Office/Business
Requires-Python: >= 3.9
License-File: LICENSE
Requires-Dist: urllib3<3.0.0,>=2.1.0
Requires-Dist: python-dateutil>=2.8.2
Requires-Dist: pydantic>=2
Requires-Dist: typing-extensions>=4.7.1
Requires-Dist: lazy-imports<2,>=1
Dynamic: author
Dynamic: home-page
Dynamic: license-file
Dynamic: requires-python
